README.md
setup.py
rolling_technical_indicators/__init__.py
rolling_technical_indicators/calc.py
rolling_technical_indicators/indicators.py
rolling_technical_indicators/model.py
rolling_technical_indicators.egg-info/PKG-INFO
rolling_technical_indicators.egg-info/SOURCES.txt
rolling_technical_indicators.egg-info/dependency_links.txt
rolling_technical_indicators.egg-info/not-zip-safe
rolling_technical_indicators.egg-info/top_level.txt