Metadata-Version: 1.0
Name: rolling-technical-indicators
Version: 0.0.1
Summary: A plugin to utilize technical indicators
Home-page: https://github.com/kburd/rolling_technical_indicators
Author: Kaleb Burd
Author-email: kalebmburd@gmail.com
License: MIT
Platform: UNKNOWN
